[
  {
    "title": "Things I Wish I Told My Mother",
    "author_1": "Susan Patterson",
    "author_2": "Susan Dilallo",
    "author_3": "James Patterson",
    "genre": "Fiction, Romance, Contemporary",
    "num_pgs": 320,
    "type": "hardcover",
    "ratings": "3.99"
  },
  {  
    "title": "The Relic",
    "author_1": "Douglas Preston",
    "author_2": "Lincoln Child",
    "genre":  "Horror, Thriller, Mystery",
    "num_pgs": 480,
    "type": "paperback",
    "ratings": "4.05"
  },
  {
    "title": "The Glass Ocean",
    "author_1": "Beatriz Williams",
    "author_2": "Lauren Willis",
    "author_3": "Karen White",
    "genre": "Historical Fiction, Romance, Mystery",
    "num_pgs": 624,
    "type": "paperback",
    "ratings": "3.88"
  }
]  
